setup.py
merge_sshconf/__init__.py
merge_sshconf/sshconf.py
merge_sshconf.egg-info/PKG-INFO
merge_sshconf.egg-info/SOURCES.txt
merge_sshconf.egg-info/dependency_links.txt
merge_sshconf.egg-info/entry_points.txt
merge_sshconf.egg-info/requires.txt
merge_sshconf.egg-info/top_level.txt