Metadata-Version: 1.0
Name: merge-sshconf
Version: 0.0.3
Summary: merge multiple ssh config to one config
Home-page: https://github.com/guoxiaoyong/merge_sshconf
Author: Guo Xiaoyong
Author-email: guo.xiaoyong@gmail.com
License: UNKNOWN
Platform: UNKNOWN
